enjoyn/__init__.py
enjoyn/_version.py
enjoyn/animator.py
enjoyn/example.py
enjoyn/preprocessor.py
enjoyn-0.1.3.dist-info/LICENSE
enjoyn-0.1.3.dist-info/METADATA
enjoyn-0.1.3.dist-info/WHEEL
enjoyn-0.1.3.dist-info/top_level.txt
enjoyn-0.1.3.dist-info/RECORD
